python_voice_assistant/Helper.py
python_voice_assistant/Listener.py
python_voice_assistant/Speaker.py
python_voice_assistant/__init__.py
python_voice_assistant/languages/en.json
python_voice_assistant/languages/ru.json
python_voice_assistant/settings.py
python_voice_assistant-1.0.1.dist-info/METADATA
python_voice_assistant-1.0.1.dist-info/WHEEL
python_voice_assistant-1.0.1.dist-info/RECORD
