Metadata-Version: 2.1
Name: python-voice-assistant
Version: 1.0.1
Summary: Create your own voice assistant like jarvis
Author: Zeph1rr
Author-email: grianton535@gmail.com
Requires-Python: >=3.10,<4.0
Classifier: Programming Language :: Python :: 3
Classifier: Programming Language :: Python :: 3.10
Classifier: Programming Language :: Python :: 3.11
Requires-Dist: loguru (>=0.7.0,<0.8.0)
Requires-Dist: numpy (>=1.24.3,<2.0.0)
Requires-Dist: pydantic (>=1.10.7,<2.0.0)
Requires-Dist: python-dotenv (>=1.0.0,<2.0.0)
Requires-Dist: silero (>=0.4.1,<0.5.0)
Requires-Dist: sounddevice (>=0.4.6,<0.5.0)
Requires-Dist: vosk (>=0.3.45,<0.4.0)
